click_threading/__init__.py
click_threading/_compat.py
click_threading/monkey.py
click_threading-0.5.0.dist-info/LICENSE
click_threading-0.5.0.dist-info/METADATA
click_threading-0.5.0.dist-info/WHEEL
click_threading-0.5.0.dist-info/top_level.txt
click_threading-0.5.0.dist-info/RECORD
