Metadata-Version: 2.1
Name: click-threading
Version: 0.5.0
Summary: Multithreaded Click apps made easy
Home-page: https://github.com/click-contrib/click-threading
Author: Markus Unterwaditzer
Author-email: markus@unterwaditzer.net
License: MIT
Platform: UNKNOWN
Classifier: Programming Language :: Python :: 3
Classifier: Programming Language :: Python :: 3.6
Classifier: Programming Language :: Python :: 3.7
Classifier: Programming Language :: Python :: 3.8
Classifier: Programming Language :: Python :: 3.9
Requires-Python: >=3.6
Requires-Dist: click (>=5.0)
